{
  "yearly_bible_calendar": {
    "months": {
      "January": {
        "1": {
          "old_testament_1": "Genesis 1:1-2:3",
          "old_testament_2": "Job 1:1-2:10",
          "new_testament": "Matthew 1"
        },
        "2": {
          "old_testament_1": "Genesis 2:4-2:25",
          "old_testament_2": "Job 2:11-3:26",
          "new_testament": "Matthew 2"
        },
        "3": {
          "old_testament_1": "Genesis 3",
          "old_testament_2": "Job 4:5",
          "new_testament": "Matthew 3"
        },
        "4": {
          "old_testament_1": "Genesis 4:1-4:26",
          "old_testament_2": "Job 6:7",
          "new_testament": "Matthew 4"
        },
        "5": {
          "old_testament_1": "Genesis 6:1-7:10",
          "old_testament_2": "Job 8",
          "new_testament": "Matthew 5:1-20"
        },
        "6": {
          "old_testament_1": "Genesis 7:11-8:19",
          "old_testament_2": "Job 9:1-10",
          "new_testament": "Matthew 5:21-48"
        },
        "7": {
          "old_testament_1": "Genesis 8:20-9:29",
          "old_testament_2": "Job 11:1-12",
          "new_testament": "Matthew 6:1-18"
        },
        "8": {
          "old_testament_1": "Genesis 10:1-11:26",
          "old_testament_2": "Job 13:1-14",
          "new_testament": "Matthew 6:19-7:6"
        },
        "9": {
          "old_testament_1": "Genesis 11:27-12:20",
          "old_testament_2": "Job 15",
          "new_testament": "Matthew 7:7-29"
        },
        "10": {
          "old_testament_1": "Genesis 13:1-14:24",
          "old_testament_2": "Job 16:1-17",
          "new_testament": "Matthew 8:1-27"
        },
        "11": {
          "old_testament_1": "Genesis 15:1-16:16",
          "old_testament_2": "Job 18:1-19",
          "new_testament": "Matthew 8:28-9:17"
        },
        "12": {
          "old_testament_1": "Genesis 17",
          "old_testament_2": "Job 20",
          "new_testament": "Matthew 9:18-38"
        },
        "13": {
          "old_testament_1": "Genesis 18",
          "old_testament_2": "Job 21",
          "new_testament": "Matthew 10:1-25"
        },
        "14": {
          "old_testament_1": "Genesis 19",
          "old_testament_2": "Job 22",
          "new_testament": "Matthew 10:26-11:1"
        },
        "15": {
          "old_testament_1": "Genesis 20:1-21:34",
          "old_testament_2": "Job 23:1-24:25",
          "new_testament": "Matthew 11:2-30"
        },
        "16": {
          "old_testament_1": "Genesis 22",
          "old_testament_2": "Job 25:1-27:23",
          "new_testament": "Matthew 12:1-21"
        },
        "17": {
          "old_testament_1": "Genesis 23",
          "old_testament_2": "Job 28",
          "new_testament": "Matthew 12:22-50"
        },
        "18": {
          "old_testament_1": "Genesis 24",
          "old_testament_2": "Job 29:1-30:31",
          "new_testament": "Matthew 13:1-23"
        },
        "19": {
          "old_testament_1": "Genesis 25",
          "old_testament_2": "Job 31",
          "new_testament": "Matthew 13:24-43"
        },
        "20": {
          "old_testament_1": "Genesis 26",
          "old_testament_2": "Job 32:1-33:33",
          "new_testament": "Matthew 13:44-14:13"
        },
        "21": {
          "old_testament_1": "Genesis 27",
          "old_testament_2": "Job 34:1-35:16",
          "new_testament": "Matthew 14:14-36"
        },
        "22": {
          "old_testament_1": "Genesis 28",
          "old_testament_2": "Job 36:1-37:24",
          "new_testament": "Matthew 15:1-28"
        },
        "23": {
          "old_testament_1": "Genesis 29",
          "old_testament_2": "Job 38:1-39:30",
          "new_testament": "Matthew 15:29-16:12"
        },
        "24": {
          "old_testament_1": "Genesis 30",
          "old_testament_2": "Job 40:1-41:34",
          "new_testament": "Matthew 16:13-17:13"
        },
        "25": {
          "old_testament_1": "Genesis 31",
          "old_testament_2": "Job 42",
          "new_testament": "Matthew 17:14-18:14"
        },
        "26": {
          "old_testament_1": "Genesis 32:1-33:16",
          "old_testament_2": "Psalms 1:1-3:8",
          "new_testament": "Matthew 18:15-35"
        },
        "27": {
          "old_testament_1": "Genesis 33:17-34:31",
          "old_testament_2": "Psalms 4:1-6:10",
          "new_testament": "Matthew 19:1-15"
        },
        "28": {
          "old_testament_1": "Genesis 35",
          "old_testament_2": "Psalms 7:1-8:9",
          "new_testament": "Matthew 19:16-20:16"
        },
        "29": {
          "old_testament_1": "Genesis 36",
          "old_testament_2": "Psalms 9:1-10:18",
          "new_testament": "Matthew 20:17-34"
        },
        "30": {
          "old_testament_1": "Genesis 37",
          "old_testament_2": "Psalms 11:1-14:7",
          "new_testament": "Matthew 21:1-32"
        },
        "31": {
          "old_testament_1": "Genesis 38",
          "old_testament_2": "Psalms 15:1-16:11",
          "new_testament": "Matthew 21:33-22:14"
        }
      },

      "February": {
        "1": {
          "Old Testament I": "Genesis 39",
          "Old Testament II": "Psalm 17",
          "New Testament": "Matthew 22:15-46"
        },
        "2": {
          "Old Testament I": "Genesis 40",
          "Old Testament II": "Psalm 18:1-29",
          "New Testament": "Matthew 23"
        },
        "3": {
          "Old Testament I": "Genesis 41:1-49",
          "Old Testament II": "Psalm 18:30-50",
          "New Testament": "Matthew 24:1-28"
        },
        "4": {
          "Old Testament I": "Genesis 41:50-42:38",
          "Old Testament II": "Psalm 19",
          "New Testament": "Matthew 24:29-51"
        },
        "5": {
          "Old Testament I": "Genesis 43",
          "Old Testament II": "Psalm 20-21",
          "New Testament": "Matthew 25:1-30"
        },
        "6": {
          "Old Testament I": "Genesis 44",
          "Old Testament II": "Psalm 22",
          "New Testament": "Matthew 25:31-26:2"
        },
        "7": {
          "Old Testament I": "Genesis 45",
          "Old Testament II": "Psalm 23-24",
          "New Testament": "Matthew 26:3-30"
        },
        "8": {
          "Old Testament I": "Genesis 46:1-47:26",
          "Old Testament II": "Psalm 25",
          "New Testament": "Matthew 26:31-57"
        },
        "9": {
          "Old Testament I": "Genesis 47:27-48:22",
          "Old Testament II": "Psalm 26-27",
          "New Testament": "Matthew 26:58-75"
        },
        "10": {
          "Old Testament I": "Genesis 49",
          "Old Testament II": "Psalm 28-29",
          "New Testament": "Matthew 27:1-26"
        },
        "11": {
          "Old Testament I": "Genesis 50",
          "Old Testament II": "Psalm 30",
          "New Testament": "Matthew 27:27-44"
        },
        "12": {
          "Old Testament I": "Exodus 1:1-2:22",
          "Old Testament II": "Psalm 31",
          "New Testament": "Matthew 27:45-66"
        },
        "13": {
          "Old Testament I": "Exodus 2:23-3:22",
          "Old Testament II": "Psalm 32-33",
          "New Testament": "Matthew 28"
        },
        "14": {
          "Old Testament I": "Exodus 4",
          "Old Testament II": "Psalm 34",
          "New Testament": "Acts 1"
        },
        "15": {
          "Old Testament I": "Exodus 5:1-6:12",
          "Old Testament II": "Psalm 35-36",
          "New Testament": "Acts 2:1-21"
        },
        "16": {
          "Old Testament I": "Exodus 6:13-7:25",
          "Old Testament II": "Psalm 37",
          "New Testament": "Acts 2:22-47"
        },
        "17": {
          "Old Testament I": "Exodus 8",
          "Old Testament II": "Psalm 38-39",
          "New Testament": "Acts 3"
        },
        "18": {
          "Old Testament I": "Exodus 9",
          "Old Testament II": "Psalm 40-41",
          "New Testament": "Acts 4:1-31"
        },
        "19": {
          "Old Testament I": "Exodus 10",
          "Old Testament II": "Psalm 42-43",
          "New Testament": "Acts 4:32-5:11"
        },
        "20": {
          "Old Testament I": "Exodus 11:1-12:20",
          "Old Testament II": "Psalm 44",
          "New Testament": "Acts 5:12-42"
        },
        "21": {
          "Old Testament I": "Exodus 12:21-51",
          "Old Testament II": "Psalm 45-46",
          "New Testament": "Acts 6"
        },
        "22": {
          "Old Testament I": "Exodus 13:1-14:4",
          "Old Testament II": "Psalm 47-48",
          "New Testament": "Acts 7:1-29"
        },
        "23": {
          "Old Testament I": "Exodus 14:5-31",
          "Old Testament II": "Psalm 49-50",
          "New Testament": "Acts 7:30-8:4"
        },
        "24": {
          "Old Testament I": "Exodus 15",
          "Old Testament II": "Psalm 51",
          "New Testament": "Acts 8:5-40"
        },
        "25": {
          "Old Testament I": "Exodus 16",
          "Old Testament II": "Psalm 52-54",
          "New Testament": "Acts 9:1-31"
        },
        "26": {
          "Old Testament I": "Exodus 17",
          "Old Testament II": "Psalm 55",
          "New Testament": "Acts 9:32-43"
        },
        "27": {
          "Old Testament I": "Exodus 18",
          "Old Testament II": "Psalm 56-57",
          "New Testament": "Acts 10:1-23"
        },
        "28": {
          "Old Testament I": "Exodus 19",
          "Old Testament II": "Psalm 58-59",
          "New Testament": "Acts 10:24-48"
        }
      },

      "March": {
        "1": {
          "Old Testament I": "Exodus 20",
          "Old Testament II": "Psalm 60-61",
          "New Testament": "Acts 11:1-18"
        },
        "2": {
          "Old Testament I": "Exodus 21",
          "Old Testament II": "Psalm 62-63",
          "New Testament": "Acts 11:19-30"
        },
        "3": {
          "Old Testament I": "Exodus 22:1-23:9",
          "Old Testament II": "Psalm 64-65",
          "New Testament": "Acts 12"
        },
        "4": {
          "Old Testament I": "Exodus 23:10-33",
          "Old Testament II": "Psalm 66-67",
          "New Testament": "Acts 13:1-25"
        },
        "5": {
          "Old Testament I": "Exodus 24",
          "Old Testament II": "Psalm 68",
          "New Testament": "Acts 13:26-52"
        },
        "6": {
          "Old Testament I": "Exodus 25",
          "Old Testament II": "Psalm 69",
          "New Testament": "Acts 14"
        },
        "7": {
          "Old Testament I": "Exodus 26:1-30",
          "Old Testament II": "Psalm 70-71",
          "New Testament": "Acts 15:1-21"
        },
        "8": {
          "Old Testament I": "Exodus 26:31-27:19",
          "Old Testament II": "Psalm 72",
          "New Testament": "Acts 15:22-35"
        },
        "9": {
          "Old Testament I": "Exodus 27:20-28:14",
          "Old Testament II": "Psalm 73",
          "New Testament": "Acts 15:36-16:15"
        },
        "10": {
          "Old Testament I": "Exodus 28:15-43",
          "Old Testament II": "Psalm 74-75",
          "New Testament": "Acts 16:16-40"
        },
        "11": {
          "Old Testament I": "Exodus 29:1-37",
          "Old Testament II": "Psalm 76-77",
          "New Testament": "Acts 17:1-15"
        },
        "12": {
          "Old Testament I": "Exodus 29:38-30:10",
          "Old Testament II": "Psalm 78:1-31",
          "New Testament": "Acts 17:16-34"
        },
        "13": {
          "Old Testament I": "Exodus 30:11-38",
          "Old Testament II": "Psalm 78:32-72",
          "New Testament": "Acts 18:1-22"
        },
        "14": {
          "Old Testament I": "Exodus 31",
          "Old Testament II": "Psalm 79-80",
          "New Testament": "Acts 18:23-19:20"
        },
        "15": {
          "Old Testament I": "Exodus 32",
          "Old Testament II": "Psalm 81-82",
          "New Testament": "Acts 19:21-41"
        },
        "16": {
          "Old Testament I": "Exodus 33:1-34:3",
          "Old Testament II": "Psalm 83-84",
          "New Testament": "Acts 20:1-16"
        },
        "17": {
          "Old Testament I": "Exodus 34:4-35",
          "Old Testament II": "Psalm 85-86",
          "New Testament": "Acts 20:17-40"
        },
        "18": {
          "Old Testament I": "Exodus 35",
          "Old Testament II": "Psalm 87-88",
          "New Testament": "Acts 21:1-16"
        },
        "19": {
          "Old Testament I": "Exodus 36",
          "Old Testament II": "Psalm 89:1-18",
          "New Testament": "Acts 21:17-38"
        },
        "20": {
          "Old Testament I": "Exodus 37",
          "Old Testament II": "Psalm 89:19-52",
          "New Testament": "Acts 22:1-21"
        },
        "21": {
          "Old Testament I": "Exodus 38",
          "Old Testament II": "Psalm 90-91",
          "New Testament": "Acts 22:22-23:11"
        },
        "22": {
          "Old Testament I": "Exodus 39",
          "Old Testament II": "Psalm 92-93",
          "New Testament": "Acts 23:12-35"
        },
        "23": {
          "Old Testament I": "Exodus 40",
          "Old Testament II": "Psalm 94-95",
          "New Testament": "Acts 24"
        },
        "24": {
          "Old Testament I": "Leviticus 1",
          "Old Testament II": "Psalm 96-98",
          "New Testament": "Acts 25:1-22"
        },
        "25": {
          "Old Testament I": "Leviticus 2",
          "Old Testament II": "Psalm 99-101",
          "New Testament": "Acts 25:23-26:11"
        },
        "26": {
          "Old Testament I": "Leviticus 3",
          "Old Testament II": "Psalm 102",
          "New Testament": "Acts 26:12-32"
        },
        "27": {
          "Old Testament I": "Leviticus 4:1-26",
          "Old Testament II": "Psalm 103",
          "New Testament": "Acts 27:1-26"
        },
        "28": {
          "Old Testament I": "Leviticus 4:27-5:13",
          "Old Testament II": "Psalm 104",
          "New Testament": "Acts 27:27-28:10"
        },
        "29": {
          "Old Testament I": "Leviticus 5:14-6:7",
          "Old Testament II": "Psalm 105",
          "New Testament": "Acts 28:11-31"
        },
        "30": {
          "Old Testament I": "Leviticus 6:8-7:10",
          "Old Testament II": "Psalm 106",
          "New Testament": "Mark 1:1-20"
        },
        "31": {
          "Old Testament I": "Leviticus 7:11-38",
          "Old Testament II": "Psalm 107",
          "New Testament": "Mark 1:21-45"
        }
      }
    }
  }
}
